firm/__init__.py
firm/firm.py
firm/miRvestigator.py
firm/pssm.py
firm/FreqFiles/HS3P.6.freq
firm/FreqFiles/HS3P.8.freq
firm/TargetPredictionDatabases/PITA/PITA_hsa-let-7a.csv
firm/TargetPredictionDatabases/PITA/PITA_hsa-let-7b.csv
firm/TargetPredictionDatabases/PITA/PITA_hsa-let-7c.csv
firm/TargetPredictionDatabases/PITA/PITA_hsa-let-7d.csv
firm/TargetPredictionDatabases/PITA/PITA_hsa-let-7e.csv
firm/TargetPredictionDatabases/PITA/PITA_hsa-let-7f.csv
firm/TargetPredictionDatabases/PITA/PITA_hsa-let-7g.csv
firm/TargetPredictionDatabases/PITA/PITA_hsa-let-7i.csv
firm/TargetPredictionDatabases/PITA/PITA_hsa-miR-1.csv
firm/TargetPredictionDatabases/PITA/PITA_hsa-miR-100.csv
firm/TargetPredictionDatabases/PITA/PITA_hsa-miR-101.csv
firm/TargetPredictionDatabases/PITA/PITA_hsa-miR-103.csv
firm/TargetPredictionDatabases/PITA/PITA_hsa-miR-105.csv
firm/TargetPredictionDatabases/PITA/PITA_hsa-miR-106a.csv
firm/TargetPredictionDatabases/PITA/PITA_hsa-miR-106b.csv
firm/TargetPredictionDatabases/PITA/PITA_hsa-miR-107.csv
firm/TargetPredictionDatabases/PITA/PITA_hsa-miR-10a.csv
firm/TargetPredictionDatabases/PITA/PITA_hsa-miR-10b.csv
firm/TargetPredictionDatabases/PITA/PITA_hsa-miR-1178.csv
firm/TargetPredictionDatabases/PITA/PITA_hsa-miR-1179.csv
firm/TargetPredictionDatabases/PITA/PITA_hsa-miR-1180.csv
firm/TargetPredictionDatabases/PITA/PITA_hsa-miR-1181.csv
firm/TargetPredictionDatabases/PITA/PITA_hsa-miR-1182.csv
firm/TargetPredictionDatabases/PITA/PITA_hsa-miR-1183.csv
firm/TargetPredictionDatabases/PITA/PITA_hsa-miR-1184.csv
firm/TargetPredictionDatabases/PITA/PITA_hsa-miR-1185.csv
firm/TargetPredictionDatabases/PITA/PITA_hsa-miR-1197.csv
firm/TargetPredictionDatabases/PITA/PITA_hsa-miR-1200.csv
firm/TargetPredictionDatabases/PITA/PITA_hsa-miR-1201.csv
firm/TargetPredictionDatabases/PITA/PITA_hsa-miR-1202.csv
firm/TargetPredictionDatabases/PITA/PITA_hsa-miR-1203.csv
firm/TargetPredictionDatabases/PITA/PITA_hsa-miR-1204.csv
isb_firm-1.0.4.dist-info/METADATA
isb_firm-1.0.4.dist-info/WHEEL
isb_firm-1.0.4.dist-info/top_level.txt
isb_firm-1.0.4.dist-info/RECORD
