Metadata-Version: 2.1
Name: isb-firm
Version: 1.0.4
Summary: Framework for inference  of regulation by miRNAs
Home-page: https://github.com/baliga-lab/firm2
Author: Baliga Lab, Institute for Systems Biology
Author-email: wwu@systemsbiology.net
Maintainer: Baliga Lab, Institute for Systems Biology
Maintainer-email: wwu@systemsbiology.net
License: LGPL V3
Keywords: miRvestigator,firm
Classifier: Development Status :: 5 - Production/Stable
Classifier: Environment :: Console
Classifier: Intended Audience :: Science/Research
Classifier: Natural Language :: English
Classifier: License :: OSI Approved :: GNU Lesser General Public License v3 or later (LGPLv3+)
Classifier: Operating System :: OS Independent
Classifier: Programming Language :: Python
Classifier: Programming Language :: Python :: 3
Classifier: Programming Language :: Python :: 3.5
Classifier: Programming Language :: Python :: Implementation :: CPython
Classifier: Topic :: Scientific/Engineering :: Bio-Informatics
Classifier: Topic :: Software Development :: Libraries :: Python Modules
